{
  "id": "38/1964",
  "type": "statute",
  "title": "Lög um heimild fyrir ríkisstjórnina til að selja Hafnarfjarðarkaupstað land jarðarinnar Áss í Hafnarfirði1)",
  "status": "in_force",
  "issued_date": "1964-05-16",
  "url": "https://www.althingi.is/lagas/nuna/1964038.html",
  "description": "Tóku gildi 13. júní 1964.",
  "provisions": [
    {
      "provision_ref": "1",
      "section": "1",
      "content": "Lög um heimild fyrir ríkisstjórnina til að selja Hafnarfjarðarkaupstað land jarðarinnar Áss í Hafnarfirði 1964 nr. 38 16. maí\nSjá Lagasafn 1990, d. 1450.\nFerill málsins á Alþingi. Frumvarp til laga.\nTóku gildi 13. júní 1964.",
      "metadata": {
        "section_format": "fallback_whole_law"
      }
    }
  ]
}
