{
  "id": "22/1966",
  "type": "statute",
  "title": "1955, um skógrækt",
  "status": "repealed",
  "issued_date": "1966-04-16",
  "url": "https://www.althingi.is/lagas/nuna/1966022.html",
  "description": "Felld úr gildi skv. <a href=\"/altext/stjt/2016.060.html\">l. 60/2016</a>, 20. gr.",
  "provisions": [
    {
      "provision_ref": "1",
      "section": "1",
      "content": "Lög um viðauka við lög nr. 3/1955, um skógrækt 1966 nr. 22 16. apríl\nFerill málsins á Alþingi. Frumvarp til laga.\nFelld úr gildi skv. l. 60/2016, 20. gr.",
      "metadata": {
        "section_format": "fallback_whole_law"
      }
    }
  ]
}
