{
  "id": "25/1967",
  "type": "statute",
  "title": "Lög um Landhelgisgæslu Íslands",
  "status": "repealed",
  "issued_date": "1967-04-22",
  "url": "https://www.althingi.is/lagas/nuna/1967025.html",
  "description": "Felld úr gildi skv. <a href=\"https://www.althingi.is/altext/stjt/2006.052.html\">l. 52/2006</a>, 30. gr.",
  "provisions": [
    {
      "provision_ref": "1",
      "section": "1",
      "content": "Lög um Landhelgisgæslu Íslands 1967 nr. 25 22. apríl\nFerill málsins á Alþingi. Frumvarp til laga.\nFelld úr gildi skv. l. 52/2006, 30. gr.",
      "metadata": {
        "section_format": "fallback_whole_law"
      }
    }
  ]
}
